pj_bridge/__init__.py
pj_bridge/__main__.py
pj_bridge/bridge.py
pj_bridge/derive_struct.py
pj_bridge/json_to_csv.py
pj_bridge/socket_client.py
pj_bridge/stream_parser.py
pj_bridge-1.0.0.dist-info/METADATA
pj_bridge-1.0.0.dist-info/WHEEL
pj_bridge-1.0.0.dist-info/entry_points.txt
pj_bridge-1.0.0.dist-info/top_level.txt
pj_bridge-1.0.0.dist-info/RECORD
