Metadata-Version: 2.4
Name: pj-bridge
Version: 1.0.0
Summary: Bridge a delimiter-framed binary stream into JSON over WebSocket for PlotJuggler (or stdout if file).
Author: Carlos Asmat, Gene Gelfand
License: MIT
Requires-Python: >=3.12
Requires-Dist: websockets<14.0,>=12.0
Provides-Extra: dev
Requires-Dist: pre-commit>=4.3.0; extra == "dev"
Requires-Dist: ruff>=0.6.8; extra == "dev"
Requires-Dist: mypy>=1.10.0; extra == "dev"
Requires-Dist: bandit>=1.7.9; extra == "dev"
Requires-Dist: pytest>=8.2.0; extra == "dev"
Requires-Dist: pytest-cov>=5.0.0; extra == "dev"
Requires-Dist: uv>=0.4; extra == "dev"
Requires-Dist: types-requests; extra == "dev"
Requires-Dist: types-setuptools; extra == "dev"
